maya_rabbitmq_package/__init__.py
maya_rabbitmq_package/rabbitmq_handler.py
maya_rabbitmq_package-0.1.2.dist-info/METADATA
maya_rabbitmq_package-0.1.2.dist-info/WHEEL
maya_rabbitmq_package-0.1.2.dist-info/top_level.txt
maya_rabbitmq_package-0.1.2.dist-info/RECORD
